steelopg/__init__.py
steelopg-0.1.0.dist-info/METADATA
steelopg-0.1.0.dist-info/WHEEL
steelopg-0.1.0.dist-info/top_level.txt
steelopg-0.1.0.dist-info/RECORD
