Metadata-Version: 2.1
Name: steelopg
Version: 0.1.0
Summary: a simple oxapay payment gateway helper
Home-page: https://github.com/steeldevlol/Steel-s-Oxapay-Payment-Gateway
Author: steeldev
Author-email: toilet@smasher.com
Classifier: Programming Language :: Python :: 3
Classifier: License :: OSI Approved :: MIT License
Classifier: Operating System :: OS Independent
Requires-Python: >=3.6
